__init__.py
setup.py
wrapper.py
wrapper_test.py
go_pkg-0.0.2.dist-info/LICENSE
go_pkg-0.0.2.dist-info/METADATA
go_pkg-0.0.2.dist-info/WHEEL
go_pkg-0.0.2.dist-info/top_level.txt
go_pkg-0.0.2.dist-info/RECORD
