Metadata-Version: 2.1
Name: go-pkg
Version: 0.0.2
Summary: A small example package to install go binaries with pip
Author-email: Robert Pupel <robert@devs-group.com>
Project-URL: Homepage, https://github.com/robert197/test-pip-with-go
Project-URL: Bug Tracker, https://github.com/robert197/test-pip-with-go/issues
Classifier: Programming Language :: Python :: 3
Classifier: License :: OSI Approved :: MIT License
Classifier: Operating System :: OS Independent
Requires-Python: >=3.7
License-File: LICENSE
